casibase-1.0.0.dist-info/licenses/LICENSE
src/__init__.py
src/file.py
src/main.py
src/prompt.py
src/properties.py
src/record.py
src/store.py
src/task.py
src/usage_info.py
casibase-1.0.0.dist-info/METADATA
casibase-1.0.0.dist-info/WHEEL
casibase-1.0.0.dist-info/top_level.txt
casibase-1.0.0.dist-info/RECORD
