Metadata-Version: 2.4
Name: casibase
Version: 1.0.0
Summary: Python SDK built for Casibase
Home-page: https://github.com/casibase/casibase-python-sdk
Author: Casibase
Author-email: Casibase <admin@casibase.org>
License:                                  Apache License
Project-URL: Home, https://github.com/casibase/casibase-python-sdk
Keywords: Casibase
Platform: any
Classifier: Intended Audience :: Developers
Classifier: License :: OSI Approved :: Apache Software License
Classifier: Operating System :: OS Independent
Classifier: Programming Language :: Python
Classifier: Programming Language :: Python :: 3.6
Classifier: Programming Language :: Python :: 3.7
Classifier: Programming Language :: Python :: 3.8
Classifier: Programming Language :: Python :: 3.9
Classifier: Programming Language :: Python :: 3.10
Classifier: Programming Language :: Python :: 3.11
Classifier: Programming Language :: Python :: 3.12
Requires-Python: >=3.6
License-File: LICENSE
Requires-Dist: requests~=2.32.0
Dynamic: license-file
